src/__init__.py
src/main.py
src/multi_panel_gui.py
src/plot_item_settings.py
src/temp.py
src/time_axis_item.py
src/time_plot_data_item.py
src/time_plot_gui.py
src/time_plot_worker.py
src/value_label_gui.py
src/viewboxv2.py
src/util/__init__.py
src/util/devicewrapper.py
src/util/dummydevice.py
src/util/workerthread.py
TimePlotGui-0.0.9.dist-info/LICENSE
TimePlotGui-0.0.9.dist-info/METADATA
TimePlotGui-0.0.9.dist-info/WHEEL
TimePlotGui-0.0.9.dist-info/top_level.txt
TimePlotGui-0.0.9.dist-info/RECORD
