Metadata-Version: 2.1
Name: TimePlotGui
Version: 0.0.9
Summary: GUI for real time data visualization
Home-page: https://github.com/kehaus/time-plot-gui
Author: Christopher Milne and Kevin Hauser
Author-email: camilne9@gmail.com
License: UNKNOWN
Platform: UNKNOWN
Classifier: Programming Language :: Python :: 3
Classifier: License :: OSI Approved :: MIT License
Classifier: Operating System :: OS Independent
Requires-Python: >=3.6
